README.md
setup.cfg
setup.py
mypackage/__init__.py
mypackage/mymodule.py
mypackage/template.txt
random_321.egg-info/PKG-INFO
random_321.egg-info/SOURCES.txt
random_321.egg-info/dependency_links.txt
random_321.egg-info/entry_points.txt
random_321.egg-info/requires.txt
random_321.egg-info/top_level.txt